snl_toadstool-1.0.0.dist-info/licenses/LICENSE
toadstool/__init__.py
toadstool/distributed.py
toadstool/utils.py
toadstool/data/__init__.py
toadstool/data/datasets.py
toadstool/data/tokenizers.py
toadstool/data/utils.py
toadstool/data/collate/__init__.py
toadstool/data/collate/mlm.py
toadstool/evaluation/__init__.py
toadstool/evaluation/margin.py
toadstool/evaluation/utils.py
toadstool/models/__init__.py
toadstool/models/argparse.py
toadstool/models/calibration.py
toadstool/models/dl_utils.py
toadstool/models/inits.py
toadstool/models/optim.py
toadstool/models/utils.py
toadstool/models/callbacks/CudaCallback.py
toadstool/models/callbacks/Debug.py
toadstool/models/callbacks/EarlyStopping.py
toadstool/models/callbacks/Evaluation.py
toadstool/models/callbacks/LearningRate.py
toadstool/models/callbacks/Monitor.py
toadstool/models/callbacks/Torch.py
toadstool/models/callbacks/Transformer.py
toadstool/models/callbacks/__init__.py
toadstool/models/zoo/MLPMixer.py
toadstool/models/zoo/RNN_classifier.py
toadstool/models/zoo/SequenceConv.py
toadstool/models/zoo/Transformer.py
toadstool/models/zoo/__init__.py
snl_toadstool-1.0.0.dist-info/METADATA
snl_toadstool-1.0.0.dist-info/WHEEL
snl_toadstool-1.0.0.dist-info/top_level.txt
snl_toadstool-1.0.0.dist-info/RECORD
