Metadata-Version: 2.4
Name: snl_toadstool
Version: 1.0.0
Summary: Boilerplate/Training library for PyTorch
Classifier: Programming Language :: Python :: 3
Classifier: Operating System :: POSIX
Requires-Python: >=3.10
License-File: LICENSE
Requires-Dist: numpy>=1.0
Requires-Dist: torch>=2.3
Requires-Dist: pandas>=1.0
Requires-Dist: scikit-learn>=0.24
Requires-Dist: matplotlib>=3.0
Requires-Dist: sentencepiece>=0.1
Requires-Dist: tqdm>=4.6
Provides-Extra: dev
Requires-Dist: pytest; extra == "dev"
Requires-Dist: ruff; extra == "dev"
Dynamic: license-file
